print_sets.py
anafora/__init__.py
anafora/cleanup.py
anafora/copy_text.py
anafora/evaluate.py
anafora/heuristic.py
anafora/labelstudio.py
anafora/regex.py
anafora/select.py
anafora/timeml.py
anafora/validate.py
venv/bin/activate_this.py
venv/lib/python3.10/site-packages/_virtualenv.py
venv/lib/python3.10/site-packages/_distutils_hack/__init__.py
venv/lib/python3.10/site-packages/_distutils_hack/override.py
venv/lib/python3.10/site-packages/pip/__init__.py
venv/lib/python3.10/site-packages/pip/__main__.py
venv/lib/python3.10/site-packages/pip/_internal/__init__.py
venv/lib/python3.10/site-packages/pip/_internal/build_env.py
venv/lib/python3.10/site-packages/pip/_internal/cache.py
venv/lib/python3.10/site-packages/pip/_internal/configuration.py
venv/lib/python3.10/site-packages/pip/_internal/exceptions.py
venv/lib/python3.10/site-packages/pip/_internal/main.py
venv/lib/python3.10/site-packages/pip/_internal/pyproject.py
venv/lib/python3.10/site-packages/pip/_internal/self_outdated_check.py
venv/lib/python3.10/site-packages/pip/_internal/wheel_builder.py
venv/lib/python3.10/site-packages/pip/_internal/cli/__init__.py
venv/lib/python3.10/site-packages/pip/_internal/cli/autocompletion.py
venv/lib/python3.10/site-packages/pip/_internal/cli/base_command.py
venv/lib/python3.10/site-packages/pip/_internal/cli/cmdoptions.py
venv/lib/python3.10/site-packages/pip/_internal/cli/command_context.py
venv/lib/python3.10/site-packages/pip/_internal/cli/main.py
venv/lib/python3.10/site-packages/pip/_internal/cli/main_parser.py
venv/lib/python3.10/site-packages/pip/_internal/cli/parser.py
venv/lib/python3.10/site-packages/pip/_internal/cli/progress_bars.py
venv/lib/python3.10/site-packages/pip/_internal/cli/req_command.py
venv/lib/python3.10/site-packages/pip/_internal/cli/spinners.py
venv/lib/python3.10/site-packages/pip/_internal/cli/status_codes.py
venv/lib/python3.10/site-packages/pip/_internal/commands/__init__.py
venv/lib/python3.10/site-packages/pip/_internal/commands/cache.py
anaforatools-1.2.0.dist-info/METADATA
anaforatools-1.2.0.dist-info/WHEEL
anaforatools-1.2.0.dist-info/licenses/LICENSE
anaforatools-1.2.0.dist-info/RECORD
