Metadata-Version: 2.1
Name: anaforatools
Version: 1.2.0
Summary: Utilities for working with Anafora annotations
Project-URL: Homepage, https://github.com/bethard/anaforatools
Project-URL: Bug Tracker, https://github.com/bethard/anaforatools/issues
Author-email: Steven Bethard <bethard@arizona.edu>, Egoitz Laparra <laparra@arizona.edu>
License:                                  Apache License
License-File: LICENSE
Classifier: License :: OSI Approved :: Apache Software License
Classifier: Operating System :: OS Independent
Classifier: Programming Language :: Python :: 3
Requires-Python: >=3.7
Requires-Dist: regex
